Fall2024/ContempCompArch/CSE4010_Labs/Lab4b/mux8x1.v
module mux_8x1(a, b, c, d, e, f, g, h, sel0, sel1, sel2, out); // Creat module called mux_8x1

    // Inputs and outputs
    input a, b, c, d, e, f, g, h, sel0, sel1, sel2;
    output out;

    // {sel2, sel1, sel0}: {0,0,0} = a, {0,0,1} = b, {0,1,0} = c, {0,1,1} = d, {1,0,0} = e, {1,0,1} = f, {1,1,0} = g, {1,1,1} = h
    assign out = sel2 ? (sel1 ? (sel0 ? h:g) : (sel0 ? f:e)):(sel1 ? (sel0 ? d:c) : (sel0 ? b:a));

endmodule // Ends module mux_8x1

Fall2024/ContempCompArch/CSE4010_Labs/Lab4b/mux8x1_tb.v
`timescale 1ns/1ns    // Sets time interval of fullSubtractor
`include "mux8x1.v"   // Links fullSubtractor.v to this file

module mux8x1_tb; // Create module called mux8x1_tb

    reg A, B, C, D, E, F, G, H, Sel0, Sel1, Sel2; // Input wires
    wire O;                                       // Output wire

    mux_8x1 uut(A, B, C, D, E, F, G, H, Sel0, Sel1, Sel2, O);  // Instantiate mux_8x1 as uut

    initial begin // Starts clock
        
        $dumpfile("mux8x1_tb"); // Sets file for output of the test
        $dumpvars(0, mux8x1_tb);

        A = 0; B = 1; C = 0; D = 1; E = 0; F = 1; G = 0; H = 1; // Set intitial values
        {Sel2, Sel1, Sel0} = 3'd0; #20; // Set Sel2 = 0, Sel1 = 0, and Sel0 = 0. Wait 20ns
        {Sel2, Sel1, Sel0} = 3'd1; #20; // Set Sel2 = 0, Sel1 = 0, and Sel0 = 1. Wait 20ns
        {Sel2, Sel1, Sel0} = 3'd2; #20; // Set Sel2 = 0, Sel1 = 1, and Sel0 = 0. Wait 20ns
        {Sel2, Sel1, Sel0} = 3'd3; #20; // Set Sel2 = 0, Sel1 = 1, and Sel0 = 1. Wait 20ns
        {Sel2, Sel1, Sel0} = 3'd4; #20; // Set Sel2 = 1, Sel1 = 0, and Sel0 = 0. Wait 20ns
        {Sel2, Sel1, Sel0} = 3'd5; #20; // Set Sel2 = 1, Sel1 = 0, and Sel0 = 1. Wait 20ns
        {Sel2, Sel1, Sel0} = 3'd6; #20; // Set Sel2 = 1, Sel1 = 1, and Sel0 = 0. Wait 20ns
        {Sel2, Sel1, Sel0} = 3'd7; #20; // Set Sel2 = 1, Sel1 = 1, and Sel0 = 1. Wait 20ns

        $display("Completed!");
    end // Ends clock
endmodule // Ends module mux8x1_tb

Fall2024/ContempCompArch/CSE4010_Labs/Lab4b/mux8x1_tb.vcd
$date
	Tue Nov 19 12:34:27 2024
$end
$version
	Icarus Verilog
$end
$timescale
	1ns
$end
$scope module mux8x1_tb $end
$var wire 1 ! O $end
$var reg 1 " A $end
$var reg 1 # B $end
$var reg 1 $ C $end
$var reg 1 % D $end
$var reg 1 & E $end
$var reg 1 ' F $end
$var reg 1 ( G $end
$var reg 1 ) H $end
$var reg 1 * Sel0 $end
$var reg 1 + Sel1 $end
$var reg 1 , Sel2 $end
$scope module uut $end
$var wire 1 " a $end
$var wire 1 # b $end
$var wire 1 $ c $end
$var wire 1 % d $end
$var wire 1 & e $end
$var wire 1 ' f $end
$var wire 1 ( g $end
$var wire 1 ) h $end
$var wire 1 * sel0 $end
$var wire 1 + sel1 $end
$var wire 1 , sel2 $end
$var wire 1 ! out $end
$upscope $end
$upscope $end
$enddefinitions $end
#0
$dumpvars
0,
0+
0*
1)
0(
1'
0&
1%
0$
1#
0"
0!
$end
#20
1!
1*
#40
0!
1+
0*
#60
1!
1*
#80
0!
1,
0+
0*
#100
1!
1*
#120
0!
1+
0*
#140
1!
1*
