Fall2024/ContempCompArch/CSE4010_Labs/Lab3a/fullAdder.v
// Simulates a half adder
module halfAdder(op1, op2, sum, carry); // Create module called halfAdder

    // inputs and outputs
    input op1, op2;
    output sum, carry;

    assign sum = op1 ^ op2;   // op1 XOR op2
    assign carry = op1 & op2; // op1 AND op2

endmodule // End module halfAdder

// Simulates a full adder
module fullAdder(A, B, carryIn, sum, carryOut);  // Create module called fullAdder

    // inputs and outputs
    input A, B, carryIn;
    output sum, carryOut;

    // intermediary wires
    wire c, d, e, f;

    halfAdder u1(A, B, c, d);        // XOR result assigned to c, AND result assigned to d
    halfAdder u2(carryIn, c, e, f);  // XOR result assigned to e, AND result assigned to f

    assign carryOut = f | d; // f OR d result assigned to carryOut
    assign sum = e;          // Assign e to sum

endmodule  // End module fullAdder

Fall2024/ContempCompArch/CSE4010_Labs/Lab3a/fullAdder_tb.v
`timescale 1 ns / 1 ns  // Sets time interval of fullAdder
`include "fullAdder.v"  // Links fullAdder.v to this file

module fullAdder_tb; // Create module called fullAdder_tb
    
    reg A, B, carryIn;   // Input wires A, B, and carryIn
    wire sum, carryOut;  // Output wires sum and carryOut

    fullAdder uut(A, B, carryIn, sum, carryOut); // Instantiate fullAdder as uut

    initial begin // Starts clock
        
        $dumpfile("fullAdder_tb.vcd"); // Sets file for output of the test
        $dumpvars(0, fullAdder_tb);

        {A, B, carryIn} = 3'd0; #20; // Set A = 0, B = 0, and carryIn = 0. Wait 20ns
        {A, B, carryIn} = 3'd1; #20; // Set A = 0, B = 0, and carryIn = 1. Wait 20ns
        {A, B, carryIn} = 3'd2; #20; // Set A = 0, B = 1, and carryIn = 0. Wait 20ns
        {A, B, carryIn} = 3'd3; #20; // Set A = 0, B = 1, and carryIn = 1. Wait 20ns
        {A, B, carryIn} = 3'd4; #20; // Set A = 1, B = 0, and carryIn = 0. Wait 20ns
        {A, B, carryIn} = 3'd5; #20; // Set A = 1, B = 0, and carryIn = 1. Wait 20ns
        {A, B, carryIn} = 3'd6; #20; // Set A = 1, B = 1, and carryIn = 0. Wait 20ns
        {A, B, carryIn} = 3'd7; #20; // Set A = 1, B = 1, and carryIn = 1. Wait 20ns
        $display("Finished additions!");
    end // Ends clock

endmodule  // End module fullAdder_tb

Fall2024/ContempCompArch/CSE4010_Labs/Lab3a/fullAdder_tb.vcd
$date
	Tue Oct 29 21:28:45 2024
$end
$version
	Icarus Verilog
$end
$timescale
	1ns
$end
$scope module fullAdder_tb $end
$var wire 1 ! sum $end
$var wire 1 " carryOut $end
$var reg 1 # A $end
$var reg 1 $ B $end
$var reg 1 % carryIn $end
$scope module uut $end
$var wire 1 # A $end
$var wire 1 $ B $end
$var wire 1 % carryIn $end
$var wire 1 " carryOut $end
$var wire 1 ! sum $end
$var wire 1 & f $end
$var wire 1 ' e $end
$var wire 1 ( d $end
$var wire 1 ) c $end
$scope module u1 $end
$var wire 1 ( carry $end
$var wire 1 # op1 $end
$var wire 1 $ op2 $end
$var wire 1 ) sum $end
$upscope $end
$scope module u2 $end
$var wire 1 & carry $end
$var wire 1 % op1 $end
$var wire 1 ) op2 $end
$var wire 1 ' sum $end
$upscope $end
$upscope $end
$upscope $end
$enddefinitions $end
#0
$dumpvars
0)
0(
0'
0&
0%
0$
0#
0"
0!
$end
#20
1!
1'
1%
#40
1)
1!
1'
1$
0%
#60
1"
0!
0'
1&
1%
#80
0"
1!
1'
0&
1#
0$
0%
#100
1"
0!
0'
1&
1%
#120
0)
1(
0!
0'
0&
1$
0%
#140
1!
1'
1%
