Fall2024/ContempCompArch/CSE4010_Labs/Lab3b/fullSubtractor.v
// Simulates a half subtractor
module halfSubtractor(op1, op2, difference, borrow); // Create module called halfSubtractor

    // inputs and outputs
    input op1, op2;
    output difference, borrow;

    assign difference = op1 ^ op2;   // op1 XOR op2
    assign borrow = !op1 & op2; // NOT op1 AND op2

endmodule // End module halfSubtractor

// Simulates a full subtractor
module fullSubtractor(A, B, borrowIn, difference, borrowOut);  // Create module called fullSubtractor

    // inputs and outputs
    input A, B, borrowIn;
    output difference, borrowOut;

    // intermediary wires
    wire c, d, e, f;

    halfSubtractor u1(A, B, c, d);        // XOR result assigned to c, AND result assigned to d
    halfSubtractor u2(borrowIn, c, e, f);  // XOR result assigned to e, AND result assigned to f

    assign borrowOut = f | d; // f OR d result assigned to borrowOut
    assign difference = e;    // Assign e to difference

endmodule  // End module fullSubtractor

Fall2024/ContempCompArch/CSE4010_Labs/Lab3b/fullSubtractor_tb.v
`timescale 1 ns / 1 ns  // Sets time interval of fullSubtractor
`include "fullSubtractor.v"  // Links fullSubtractor.v to this file

module fullSubtractor_tb; // Create module called fullSubtractor_tb
    
    reg A, B, borrowIn;   // Input wires A, B, and borrowIn
    wire difference, borrowOut;  // Output wires difference and borrowOut

    fullSubtractor uut(A, B, borrowIn, difference, borrowOut); // Instantiate fullSubtractor as uut

    initial begin // Starts clock
        
        $dumpfile("fullSubtractor_tb.vcd"); // Sets file for output of the test
        $dumpvars(0, fullSubtractor_tb);

        {A, B, borrowIn} = 3'd0; #20; // Set A = 0, B = 0, and borrowIn = 0. Wait 20ns
        {A, B, borrowIn} = 3'd1; #20; // Set A = 0, B = 0, and borrowIn = 1. Wait 20ns
        {A, B, borrowIn} = 3'd2; #20; // Set A = 0, B = 1, and borrowIn = 0. Wait 20ns
        {A, B, borrowIn} = 3'd3; #20; // Set A = 0, B = 1, and borrowIn = 1. Wait 20ns
        {A, B, borrowIn} = 3'd4; #20; // Set A = 1, B = 0, and borrowIn = 0. Wait 20ns
        {A, B, borrowIn} = 3'd5; #20; // Set A = 1, B = 0, and borrowIn = 1. Wait 20ns
        {A, B, borrowIn} = 3'd6; #20; // Set A = 1, B = 1, and borrowIn = 0. Wait 20ns
        {A, B, borrowIn} = 3'd7; #20; // Set A = 1, B = 1, and borrowIn = 1. Wait 20ns
        $display("Finished subtractions!");
    end // Ends clock

endmodule  // End module fullSubtractor_tb

Fall2024/ContempCompArch/CSE4010_Labs/Lab3b/fullSubtractor_tb.vcd
$date
	Tue Oct 29 21:33:14 2024
$end
$version
	Icarus Verilog
$end
$timescale
	1ns
$end
$scope module fullSubtractor_tb $end
$var wire 1 ! difference $end
$var wire 1 " borrowOut $end
$var reg 1 # A $end
$var reg 1 $ B $end
$var reg 1 % borrowIn $end
$scope module uut $end
$var wire 1 # A $end
$var wire 1 $ B $end
$var wire 1 % borrowIn $end
$var wire 1 " borrowOut $end
$var wire 1 ! difference $end
$var wire 1 & f $end
$var wire 1 ' e $end
$var wire 1 ( d $end
$var wire 1 ) c $end
$scope module u1 $end
$var wire 1 ( borrow $end
$var wire 1 ) difference $end
$var wire 1 # op1 $end
$var wire 1 $ op2 $end
$upscope $end
$scope module u2 $end
$var wire 1 & borrow $end
$var wire 1 ' difference $end
$var wire 1 % op1 $end
$var wire 1 ) op2 $end
$upscope $end
$upscope $end
$upscope $end
$enddefinitions $end
#0
$dumpvars
0)
0(
0'
0&
0%
0$
0#
0"
0!
$end
#20
1!
1'
1%
#40
1&
1"
1)
1(
1!
1'
1$
0%
#60
0!
0'
0&
1%
#80
0(
1!
1'
1&
1#
0$
0%
#100
0"
0!
0'
0&
1%
#120
0"
0)
0!
0'
0&
1$
0%
#140
1!
1'
1%
